smart_media_manager/__init__.py
smart_media_manager/cli.py
smart_media_manager/format_compatibility.json
smart_media_manager/format_registry.json
smart_media_manager/format_registry.py
smart_media_manager/format_rules.py
smart_media_manager/metadata_registry.json
smart_media_manager/metadata_registry.py
smart_media_manager/uuid_generator.py
smart_media_manager-0.5.45.dist-info/licenses/LICENSE
smart_media_manager-0.5.45.dist-info/METADATA
smart_media_manager-0.5.45.dist-info/WHEEL
smart_media_manager-0.5.45.dist-info/entry_points.txt
smart_media_manager-0.5.45.dist-info/top_level.txt
smart_media_manager-0.5.45.dist-info/RECORD
