Metadata-Version: 2.4
Name: smart-media-manager
Version: 0.5.45
Summary: A macOS CLI that audits media folders, fixes extensions, and imports into Apple Photos
Requires-Python: >=3.12
License-File: LICENSE
Requires-Dist: filetype>=1.2.0
Requires-Dist: puremagic>=1.30
Requires-Dist: isbinary>=1.0.1
Requires-Dist: python-magic>=0.4.27
Requires-Dist: pyfsig>=1.1.1
Requires-Dist: pillow>=12.0.0
Requires-Dist: rawpy>=0.25.1
Provides-Extra: enhanced
Dynamic: license-file
